<?xml version='1.0' encoding='UTF-8'?>
<tg4w version="0.38.2">
    <actions>

        <action type="goto" refresh="true" step="0">
            <xpath><![CDATA[window.location.href]]></xpath>
            <value><![CDATA[http://localhost:8888/talent-studio/orgbuilder/browseposition.htm?navigator.organisationUnitLabel=Led+Zeppelin&navigator.organisationUnitId=16&navigator.notSubmit=false&menu_p=]]></value>
        </action>

        <action type="verify-title" step="1">
            <xpath><![CDATA[*]]></xpath>
            <value><![CDATA[Talent Studio - Browse Positions]]></value>
        </action>
        <action type="assert-text-exists" step="2">
            <xpath><![CDATA[*]]></xpath>
            <value><![CDATA[Summary of Bass Guitar]]></value>
        </action>
        <action type="assert-text-exists" step="3">
            <xpath><![CDATA[*]]></xpath>
            <value><![CDATA[Led Zeppelin]]></value>
        </action>
        <action type="assert-text-exists" step="4">
            <xpath><![CDATA[*]]></xpath>
            <value><![CDATA[John Paul Jones]]></value>
        </action>
        <action type="click" refresh="true" step="5">
            <xpath><![CDATA[*/FORM[@ID="details_frm"]/INPUT[@ID="btn_details"]]]></xpath>
            <value><![CDATA[details_frm]]></value>
        </action>
        <action type="verify-title" step="6">
            <xpath><![CDATA[*]]></xpath>
            <value><![CDATA[Talent Studio - Edit Position]]></value>
        </action>

        <!-- set title and org unit toblank - validation failure expected -->
        <action type="fill" step="7">
            <xpath><![CDATA[*/FORM[@ID="editposda"]/*/INPUT[@TYPE="text" and @NAME="position.title"]]]></xpath>
            <value><![CDATA[]]></value>
        </action>
        <action type="fill" step="8">
            <xpath><![CDATA[*/FORM[@ID="editposda"]/*/INPUT[@TYPE="hidden" and @NAME="position.organisationUnit.id"]]]></xpath>
            <value><![CDATA[]]></value>
        </action>
        <action type="click" refresh="true" step="9">
            <xpath><![CDATA[*/FORM[@ID="editposda"]/*/INPUT[@NAME="_edit" and @VALUE="Save"]]]></xpath>
            <value><![CDATA[_edit]]></value>
        </action>
        <action type="verify-title" step="10">
            <xpath><![CDATA[*]]></xpath>
            <value><![CDATA[Talent Studio - Edit Position]]></value>
        </action>
        <action type="assert-text-exists" step="11">
            <xpath><![CDATA[*]]></xpath>
            <value><![CDATA[Title is a required field.]]></value>
        </action>
        <action type="assert-text-exists" step="12">
            <xpath><![CDATA[*]]></xpath>
            <value><![CDATA[You must select a parent organisation unit.]]></value>
        </action>

        <!-- set title and org unit and comments and save -->
        <action type="fill" step="13">
            <xpath><![CDATA[*/FORM[@ID="editposda"]/*/INPUT[@TYPE="text" and @NAME="position.title"]]]></xpath>
            <value><![CDATA[Bass Guitar]]></value>
        </action>
        <action type="fill" step="14">
            <xpath><![CDATA[*/FORM[@ID="editposda"]/*/INPUT[@TYPE="hidden" and @NAME="position.organisationUnit.id"]]]></xpath>
            <value><![CDATA[16]]></value>
        </action>
        <action type="fill" step="15">
            <xpath><![CDATA[*/FORM[@ID="editposda"]/*/TEXTAREA[@NAME="position.comments"]]]></xpath>
            <value><![CDATA[This is a test]]></value>
        </action>
        <action type="click" refresh="true" step="16">
            <xpath><![CDATA[*/FORM[@ID="editposda"]/*/INPUT[@NAME="_edit" and @VALUE="Save"]]]></xpath>
            <value><![CDATA[_edit]]></value>
        </action>
        <action type="verify-title" step="17">
            <xpath><![CDATA[*]]></xpath>
            <value><![CDATA[Talent Studio - Browse Positions]]></value>
        </action>
        <action type="assert-text-exists" step="18">
            <xpath><![CDATA[*]]></xpath>
            <value><![CDATA[This is a test]]></value>
        </action>
    </actions>
</tg4w>